mindware/__init__.py
mindware/__main__.py
mindware/automl.py
mindware/base_estimator.py
mindware/estimators.py
mindware/pkginfo.py
mindware/py.typed
mindware/blocks/__init__.py
mindware/blocks/abstract_block.py
mindware/blocks/alternating_block.py
mindware/blocks/block_utils.py
mindware/blocks/conditioning_block.py
mindware/blocks/joint_block.py
mindware/components/__init__.py
mindware/components/computation/__init__.py
mindware/components/computation/parallel_evaluator.py
mindware/components/computation/parallel_fetcher.py
mindware/components/computation/parallel_process.py
mindware/components/computation/base/__init__.py
mindware/components/computation/base/nondaemonic_processpool.py
mindware/components/ensemble/__init__.py
mindware/components/ensemble/bagging.py
mindware/components/ensemble/base_ensemble.py
mindware/components/ensemble/blending.py
mindware/components/ensemble/ensemble_bulider.py
mindware/components/ensemble/ensemble_selection.py
mindware/components/ensemble/stacking.py
mindware/components/ensemble/unnamed_ensemble.py
mindware/components/evaluators/__init__.py
mindware/components/evaluators/base_evaluator.py
mindware/components/evaluators/cls_evaluator.py
mindware/components/evaluators/evaluate_func.py
mindware/components/evaluators/rgs_evaluator.py
mindware/components/feature_engineering/__init__.py
mindware/components/feature_engineering/fe_pipeline.py
mindware/components/feature_engineering/parse.py
mindware/components/feature_engineering/task_space.py
mindware/components/feature_engineering/transformation_graph.py
mindware/components/feature_engineering/transformations/__init__.py
mindware/components/feature_engineering/transformations/base_transformer.py
mindware/components/feature_engineering/transformations/continous_discretizer.py
mindware/components/feature_engineering/transformations/discrete_categorizer.py
mindware/components/feature_engineering/transformations/empty_transformer.py
mindware-0.5.0.dist-info/LICENSE
mindware-0.5.0.dist-info/METADATA
mindware-0.5.0.dist-info/WHEEL
mindware-0.5.0.dist-info/entry_points.txt
mindware-0.5.0.dist-info/top_level.txt
mindware-0.5.0.dist-info/RECORD
