Metadata-Version: 2.1
Name: mindware
Version: 0.5.0
Summary: MindWare: Towards Efficient AutoML System.
Home-page: https://github.com/thomas-young-2013/mindware
Author: AutoML Researchers @ DAIR
Author-email: liyang.cs@pku.edu.cn
License: MIT
Keywords: AutoML; Machine Learning; Deep Learning
Platform: UNKNOWN
Requires-Python: >=3.6.0
Requires-Dist: setuptools
Requires-Dist: cython
Requires-Dist: nose
Requires-Dist: liac-arff
Requires-Dist: psutil
Requires-Dist: pyyaml
Requires-Dist: statsmodels
Requires-Dist: lightgbm
Requires-Dist: terminaltables
Requires-Dist: scikit-learn (>=0.22.1)
Requires-Dist: tabulate (>=0.8.5)
Requires-Dist: ConfigSpace (<0.5,>=0.4.12)
Requires-Dist: pandas (>=0.24.0)
Requires-Dist: numpy (>=1.7.1)
Requires-Dist: scipy (>=0.18.1)
Requires-Dist: scikit-optimize (>=0.8)
Requires-Dist: openbox
Provides-Extra: dev
